ebooklib/__init__.py
ebooklib/epub.py
ebooklib/utils.py
ebooklib/plugins/__init__.py
ebooklib/plugins/base.py
ebooklib/plugins/booktype.py
ebooklib/plugins/sourcecode.py
ebooklib/plugins/standard.py
ebooklib/plugins/tidyhtml.py
ebooklib_autoupdate-0.18.3.dist-info/METADATA
ebooklib_autoupdate-0.18.3.dist-info/WHEEL
ebooklib_autoupdate-0.18.3.dist-info/top_level.txt
ebooklib_autoupdate-0.18.3.dist-info/RECORD
