Metadata-Version: 2.4
Name: ebooklib-autoupdate
Version: 0.18.3
Summary: Ebook library which can handle EPUB2/EPUB3 format
Author: Sergey Markelov
Author-email: Aleksandar Erkalovic <aerkalov@gmail.com>, Borko Jandras <bjandras@gmail.com>, the-happy-hippo <th3hh0@gmail.com>, Daniel James <daniel@64studio.com>, Mikhail Gusarov <dottedmag@dottedmag.net>, Raymond Yee <raymond.yee@gmail.com>, Chris Grice <chris@chrisgrice.com>, Fernando Wime <fernando.d@wime.com.mx>, Andy Roberts <andy.roberts.uk@gmail.com>, Tom McLean <tom.a.mclean@gmail.com>, Travis L <leleu@industrialinterface.com>, Helmy Giacoman <helmygb@gmail.com>, clach04 <Chris.Clark@a
Maintainer-email: Ashlynn Antrobus <ashlynn@prosepal.io>, Aleksandar Erkalovic <aerkalov@gmail.com>
License: AGPL-3.0
Project-URL: Homepage, https://github.com/aerkalov/ebooklib
Project-URL: Documentation, https://ebooklib.readthedocs.io
Keywords: ebook,epub
Classifier: Development Status :: 4 - Beta
Classifier: Intended Audience :: Developers
Classifier: Operating System :: OS Independent
Classifier: Programming Language :: Python :: 3.6
Classifier: Programming Language :: Python :: 3.7
Classifier: Programming Language :: Python :: 3.8
Classifier: Programming Language :: Python :: 3.9
Classifier: Programming Language :: Python :: 3.10
Classifier: Programming Language :: Python :: 3.11
Classifier: Programming Language :: Python :: 3.12
Classifier: Topic :: Software Development :: Libraries :: Python Modules
Requires-Python: >=3.6
Requires-Dist: lxml>=4.9.0
Requires-Dist: six>=1.16.0
